src/gort_core_plugin_es/__init__.py
rh_gort_core_plugin_es-0.0.0.dist-info/METADATA
rh_gort_core_plugin_es-0.0.0.dist-info/WHEEL
rh_gort_core_plugin_es-0.0.0.dist-info/licenses/LICENSE
rh_gort_core_plugin_es-0.0.0.dist-info/RECORD
